jupytray/__init__.py
jupytray/__main__.py
jupytray/control_window.py
jupytray/icon.py
jupytray/notebook_server.py
jupytray/shortcuts.py
jupytray/tray_app.py
jupytray-0.8.dist-info/License
jupytray-0.8.dist-info/METADATA
jupytray-0.8.dist-info/WHEEL
jupytray-0.8.dist-info/entry_points.txt
jupytray-0.8.dist-info/top_level.txt
jupytray-0.8.dist-info/RECORD
