Metadata-Version: 2.1
Name: jupytray
Version: 0.8
Summary: Run the Jupyter notebook server as a little app in the system tray
Home-page: https://github.com/tfiers/jupytray
Author: Tomas Fiers
Author-email: tomas.fiers@gmail.com
License: UNKNOWN
Project-URL: Source Code, https://github.com/tfiers/jupytray
Platform: UNKNOWN
Classifier: License :: OSI Approved :: MIT License
Classifier: Programming Language :: Python :: 3
Classifier: Operating System :: Microsoft :: Windows
Requires-Dist: notebook
Requires-Dist: click (~=7.1)
Requires-Dist: pywin32
Requires-Dist: winshell (==0.6)
